Workbook

Sheet README
A1: Capital Group — Institutional CRM (MOCK / SYNTHETIC DATA)
A3: PURPOSE
A4: Sample customer-relationship-management (CRM) dataset modeled on how a large active asset
A5: manager (Capital Group, home of American Funds) would structure institutional client data.
A7: IMPORTANT — THIS DATA IS NOT REAL
A8: • Capital Group does not publish a client list; specific client identities are confidential.
A9: • Every institution, person, email, phone number, AUM figure, mandate and note below is FICTIONAL.
A10: • Account TYPES (public pension, corporate DB/DC, endowment, insurance, sub-advisory, etc.) and
A11: Capital Group STRATEGY names are real/public; they are used only to make the mock realistic.
A12: • The only real public reference point used for context: U.S. public pension funds disclose their
A13: external managers (e.g., NY State Common Retirement Fund publicly reported a ~$2.1B Capital Group
A14: international-equity account, terminated June 2025). No such real records are reproduced here.
... A23: Generated: 2026-06-04 | Records: 25 accounts, 50 contacts, 29 opportunities, 69 activities

Sheet Accounts
A1: Account ID | B1: Account Name | C1: Type | D1: Region | E1: Country/State | F1: AUM with CG ($mm) | G1: Tier | H1: Client Since | I1: Primary Strategy | J1: Relationship Mgr | K1: Consultant | L1: Status
A2: ACC-1001 | B2: Northgate County Employees' Retirement System | C2: Public Pension (DB) | D2: Americas | E2: USA - OH | F2: 685.4 | G2: Strategic | H2: 2005 | I2: EuroPacific Growth (Intl Equity) | J2: Marcus Hale | K2: In-house | L2: Active
A3: ACC-1002 | B3: State of Calderon Teachers' Retirement Fund | C3: Public Pension (DB) | D3: Americas | E3: USA - TX | F3: 0 | G3: Strategic | I3: Capital Group Core Plus Income (Fixed Income) | J3: Diane Okafor | K3: Mercer | L3: Prospect
A4: ACC-1003 | B4: Westhaven Municipal Pension Trust | C4: Public Pension (DB) | D4: Americas | E4: USA - CA | F4: 1230.2 | G4: Core | H4: 1998 | I4: Capital Group Multi-Sector Income | J4: Tom Brennan | K4: In-house | L4: Active
A5: ACC-1004 | B5: Riverbend Public Employees Pension | C5: Public Pension (DB) | D5: Americas | E5: USA - IL | F5: 0 | G5: Core | I5: The Bond Fund of America Strategy (Core Bond) | J5: Sofia Marchetti | K5: Mercer | L5: Prospect
A6: ACC-1005 | B6: Meridian Aerospace Pension Trust | C6: Corporate Pension (DB) | D6: Americas | E6: USA - WA | F6: 839.7 | G6: Developing | H6: 2002 | I6: Capital Group International Equity | J6: Daniel Cho | K6: Aon | L6: Active
A7: ACC-1006 | B7: Halcyon Industries Retirement Plan | C7: Corporate Pension (DB) | D7: Americas | E7: USA - MI | F7: 884 | G7: Core | H7: 2009 | I7: Capital Group Emerging Markets Debt | J7: Sofia Marchetti | K7: Mercer | L7: Active
A8: ACC-1007 | B8: Brightline Logistics 401(k) Plan | C8: Corporate DC / 401(k) | D8: Americas | E8: USA - GA | F8: 2336.4 | G8: Core | H8: 2010 | I8: Capital Group Growth (US Equity) | J8: Sofia Marchetti | K8: In-house | L8: At Risk
A9: ACC-1008 | B9: Verdant Foods Inc. Savings Plan | C9: Corporate DC / 401(k) | D9: Americas | E9: USA - MN | F9: 0 | G9: Developing | I9: Capital Group World Dividend Growers | J9: Tom Brennan | K9: Aon | L9: Prospect
A10: ACC-1009 | B10: Cordova Technologies 401(k) Plan | C10: Corporate DC / 401(k) | D10: Americas | E10: USA - CA | F10: 1863.3 | G10: Developing | H10: 2000 | I10: Capital Group International Equity | J10: Marcus Hale | K10: RVK | L10: Active
A11: ACC-1010 | B11: Ashford University Endowment | C11: Endowment & Foundation | D11: Americas | E11: USA - MA | F11: 2007.7 | G11: Core | H11: 2003 | I11: Capital Group World Dividend Growers | J11: Daniel Cho | K11: NEPC | L11: Active
A12: ACC-1011 | B12: Lakemont College Endowment Fund | C12: Endowment & Foundation | D12: Americas | E12: USA - NY | F12: 1651.6 | G12: Developing | H12: 2000 | I12: Capital Group Emerging Markets Debt | J12: Priya Venkatesan | K12: WTW | L12: Active
A13: ACC-1012 | B13: The Pemberton Family Foundation | C13: Endowment & Foundation | D13: Americas | E13: USA - CT | F13: 932.4 | G13: Strategic | H13: 2018 | I13: American Funds Target Date Series (DC) | J13: Tom Brennan | K13: In-house | L13: Active
A14: ACC-1013 | B14: Sentinel Mutual Life General Account | C14: Insurance General Account | D14: Americas | E14: USA - NJ | F14: 1870.2 | G14: Developing | H14: 2005 | I14: Capital Group New Perspective (Global Equity) | J14: Daniel Cho | K14: RVK | L14: Active
A15: ACC-1014 | B15: Aegis Casualty & Surety Co. | C15: Insurance General Account | D15: Americas | E15: USA - CT | F15: 2194.6 | G15: Strategic | H15: 2016 | I15: American Funds Target Date Series (DC) | J15: Daniel Cho | K15: NEPC | L15: Active
A16: ACC-1015 | B16: Crowne Variable Annuity Platform | C16: Sub-Advisory | D16: Americas | E16: USA - IA | F16: 2197.9 | G16: Core | H16: 2012 | I16: EuroPacific Growth (Intl Equity) | J16: Sofia Marchetti | K16: Callan | L16: At Risk
A17: ACC-1016 | B17: Beacon Wealth Model Portfolios | C17: Sub-Advisory | D17: Americas | E17: USA - NC | F17: 1309.7 | G17: Developing | H17: 2021 | I17: Capital Group Emerging Markets Debt | J17: Renee Lambert | K17: Verus | L17: Active
A18: ACC-1017 | B18: Stonebridge Health System Operating Fund | C18: Healthcare System | D18: Americas | E18: USA - PA | F18: 2393.7 | G18: Core | H18: 2002 | I18: Capital Group Multi-Sector Income | J18: Owen Fitzgerald | K18: Aon | L18: At Risk
A19: ACC-1018 | B19: Cascade Medical Group Pension | C19: Healthcare System | D19: Americas | E19: USA - OR | F19: 396.5 | G19: Developing | H19: 2003 | I19: Capital Income Builder (Income) | J19: Renee Lambert | K19: Verus | L19: Active
A20: ACC-1019 | B20: Maple Provincial Pension Board | C20: Public Pension (DB) | D20: Americas | E20: Canada - ON | F20: 1444.3 | G20: Core | H20: 2012 | I20: Capital Group Multi-Sector Income | J20: Sofia Marchetti | K20: WTW | L20: Active
A21: ACC-1020 | B21: Helvetia Pensionskasse | C21: Corporate Pension (DB) | D21: EMEA | E21: Switzerland | F21: 305.9 | G21: Developing | H21: 2015 | I21: Capital Group US Core Equity | J21: Daniel Cho | K21: Aon | L21: Active
... A26: ACC-1025 | B26: United Transit Workers Annuity Fund | C26: Taft-Hartley / Union | D26: Americas | E26: USA - NY | F26: 2274.5 | G26: Developing | H26: 2000 | I26: American Funds Target Date Series (DC) | J26: Owen Fitzgerald | K26: Aon | L26: Active
E27: TOTAL | F27: =SUM(F2:F26) -> 29823

Sheet Contacts
A1: Contact ID | B1: Account ID | C1: Account Name | D1: First Name | E1: Last Name | F1: Title | G1: Role | H1: Email | I1: Phone | J1: Last Contacted
A2: CON-2001 | B2: ACC-1001 | C2: Northgate County Employees' Retirement System | D2: John | E2: Sato | F2: Director of Investments | G2: Decision Maker | H2: j.sato@northgate.example.org | I2: +1 (555) 762-3705 | J2: 2026-03-28
A3: CON-2002 | B3: ACC-1001 | C3: Northgate County Employees' Retirement System | D3: Lucas | E3: Castellano | F3: Investment Committee Chair | G3: Gatekeeper | H3: l.castellano@northgate.example.org | I3: +1 (555) 416-9835 | J3: 2025-12-09
A4: CON-2003 | B4: ACC-1001 | C4: Northgate County Employees' Retirement System | D4: Mateo | E4: Tanaka | F4: Director of Investments | G4: Decision Maker | H4: m.tanaka@northgate.example.org | I4: +1 (555) 887-7118 | J4: 2026-02-11
A5: CON-2004 | B5: ACC-1002 | C5: State of Calderon Teachers' Retirement Fund | D5: Patricia | E5: Schmidt | F5: Portfolio Manager - Public Equities | G5: Influencer | H5: p.schmidt@state.example.org | I5: +1 (555) 265-6539 | J5: 2026-05-29
A6: CON-2005 | B6: ACC-1002 | C6: State of Calderon Teachers' Retirement Fund | D6: Lisa | E6: Schmidt | F6: Plan Administrator | G6: Gatekeeper | H6: l.schmidt@state.example.org | I6: +1 (555) 425-1117 | J6: 2026-05-16
A7: CON-2006 | B7: ACC-1002 | C7: State of Calderon Teachers' Retirement Fund | D7: Liam | E7: Mitchell | F7: Board Trustee | G7: Gatekeeper | H7: l.mitchell@state.example.org | I7: +1 (555) 269-1514 | J7: 2026-03-11
A8: CON-2007 | B8: ACC-1003 | C8: Westhaven Municipal Pension Trust | D8: Linda | E8: Larsson | F8: Plan Administrator | G8: Gatekeeper | H8: l.larsson@westhaven.example.org | I8: +1 (555) 697-4510 | J8: 2026-01-16
A9: CON-2008 | B9: ACC-1004 | C9: Riverbend Public Employees Pension | D9: Chen | E9: Hoffman | F9: Plan Administrator | G9: Gatekeeper | H9: c.hoffman@riverbend.example.org | I9: +1 (555) 684-4981 | J9: 2026-02-02
A10: CON-2009 | B10: ACC-1005 | C10: Meridian Aerospace Pension Trust | D10: Patricia | E10: Caldwell | F10: VP, Pension Investments | G10: Decision Maker | H10: p.caldwell@meridian.example.org | I10: +1 (555) 641-6804 | J10: 2026-02-15
A11: CON-2010 | B11: ACC-1005 | C11: Meridian Aerospace Pension Trust | D11: Joseph | E11: Moreau | F11: Senior Investment Officer | G11: Influencer | H11: j.moreau@meridian.example.org | I11: +1 (555) 889-2612 | J11: 2026-05-19
A12: CON-2011 | B12: ACC-1006 | C12: Halcyon Industries Retirement Plan | D12: William | E12: Caldwell | F12: Board Trustee | G12: Gatekeeper | H12: w.caldwell@halcyon.example.org | I12: +1 (555) 396-4116 | J12: 2026-01-17
... A51: CON-2050 | B51: ACC-1025 | C51: United Transit Workers Annuity Fund | D51: Aisha | E51: Patel | F51: Plan Administrator | G51: Gatekeeper | H51: a.patel@united.example.org | I51: +1 (555) 782-5930 | J51: 2026-02-20

Sheet Pipeline
A1: Opportunity ID | B1: Account Name | C1: Opportunity | D1: Strategy | E1: Mandate Size ($mm) | F1: Stage | G1: Probability | H1: Weighted ($mm) | I1: Expected Close | J1: Owner
A2: OPP-3001 | B2: Northgate County Employees' Retirement System | C2: Capital Group US Core Equity mandate | D2: Capital Group US Core Equity | E2: 177.4 | F2: RFP Submitted | G2: 0.4 | H2: =E2*G2 -> 70.96 | I2: 2027-01-26 | J2: Marcus Hale
A3: OPP-3002 | B3: State of Calderon Teachers' Retirement Fund | C3: The Bond Fund of America Strategy mandate | D3: The Bond Fund of America Strategy (Core Bond) | E3: 345.6 | F3: Finals Presentation | G3: 0.6 | H3: =E3*G3 -> 207.36 | I3: 2026-07-23 | J3: Diane Okafor
A4: OPP-3003 | B4: State of Calderon Teachers' Retirement Fund | C4: The Bond Fund of America Strategy mandate | D4: The Bond Fund of America Strategy (Core Bond) | E4: 600.5 | F4: Due Diligence | G4: 0.8 | H4: =E4*G4 -> 480.4 | I4: 2026-06-30 | J4: Diane Okafor
A5: OPP-3004 | B5: Riverbend Public Employees Pension | C5: Capital Group International Equity mandate | D5: Capital Group International Equity | E5: 512.8 | F5: Prospecting | G5: 0.1 | H5: =E5*G5 -> 51.28 | I5: 2026-07-29 | J5: Sofia Marchetti
A6: OPP-3005 | B6: Riverbend Public Employees Pension | C6: Capital Group International Equity mandate | D6: Capital Group International Equity | E6: 131.8 | F6: Lost | G6: 0 | H6: =E6*G6 -> 0 | I6: 2026-04-28 | J6: Sofia Marchetti
A7: OPP-3006 | B7: Meridian Aerospace Pension Trust | C7: Capital Group Growth mandate | D7: Capital Group Growth (US Equity) | E7: 355.2 | F7: Due Diligence | G7: 0.8 | H7: =E7*G7 -> 284.16 | I7: 2027-02-21 | J7: Daniel Cho
A8: OPP-3007 | B8: Meridian Aerospace Pension Trust | C8: Capital Group International Equity mandate | D8: Capital Group International Equity | E8: 545.8 | F8: Due Diligence | G8: 0.8 | H8: =E8*G8 -> 436.64 | I8: 2026-10-18 | J8: Daniel Cho
A9: OPP-3008 | B9: Halcyon Industries Retirement Plan | C9: Capital Income Builder mandate | D9: Capital Income Builder (Income) | E9: 523.5 | F9: Qualification | G9: 0.25 | H9: =E9*G9 -> 130.875 | I9: 2026-05-29 | J9: Sofia Marchetti
A10: OPP-3009 | B10: Verdant Foods Inc. Savings Plan | C10: Capital Group Multi-Sector Income mandate | D10: Capital Group Multi-Sector Income | E10: 205.7 | F10: Prospecting | G10: 0.1 | H10: =E10*G10 -> 20.57 | I10: 2026-06-06 | J10: Tom Brennan
A11: OPP-3010 | B11: Verdant Foods Inc. Savings Plan | C11: EuroPacific Growth mandate | D11: EuroPacific Growth (Intl Equity) | E11: 606 | F11: Finals Presentation | G11: 0.6 | H11: =E11*G11 -> 363.6 | I11: 2027-01-01 | J11: Tom Brennan
A12: OPP-3011 | B12: Ashford University Endowment | C12: American Funds Target Date Series mandate | D12: American Funds Target Date Series (DC) | E12: 671.7 | F12: Due Diligence | G12: 0.8 | H12: =E12*G12 -> 537.36 | I12: 2026-11-09 | J12: Daniel Cho
A13: OPP-3012 | B13: Ashford University Endowment | C13: Capital Group Multi-Sector Income mandate | D13: Capital Group Multi-Sector Income | E13: 348.3 | F13: Lost | G13: 0 | H13: =E13*G13 -> 0 | I13: 2026-06-25 | J13: Daniel Cho
... A30: OPP-3029 | B30: United Transit Workers Annuity Fund | C30: Capital Income Builder mandate | D30: Capital Income Builder (Income) | E30: 54.2 | F30: Lost | G30: 0 | H30: =E30*G30 -> 0 | I30: 2026-04-20 | J30: Owen Fitzgerald
D31: TOTAL | E31: =SUM(E2:E30) -> 11619.4 | H31: =SUM(H2:H30) -> 5277.43

Sheet Activities
A1: Activity ID | B1: Date | C1: Account Name | D1: Contact | E1: Type | F1: Subject | G1: Owner | H1: Next Step
A2: ACT-4008 | B2: 2026-05-31 | C2: Riverbend Public Employees Pension | D2: Chen Hoffman | E2: Meeting | F2: Board education session | G2: Sofia Marchetti | H2: Share peer benchmarking data
A3: ACT-4040 | B3: 2026-05-19 | C3: Crowne Variable Annuity Platform | D3: Aisha Caldwell | E3: Call | F3: Mandate funding logistics | G3: Sofia Marchetti | H3: No action - relationship healthy
A4: ACT-4056 | B4: 2026-05-11 | C4: Nordmark National Pension Fund | D4: Emma Delgado | E4: Portfolio Review | F4: Annual portfolio review completed | G4: Sofia Marchetti | H4: Schedule finals presentation
A5: ACT-4004 | B5: 2026-05-07 | C5: State of Calderon Teachers' Retirement Fund | D5: Lisa Schmidt | E5: Call | F5: Performance check-in call | G5: Diane Okafor | H5: No action - relationship healthy
A6: ACT-4002 | B6: 2026-05-05 | C6: Northgate County Employees' Retirement System | D6: Mateo Tanaka | E6: Conference | F6: Pension consultant conference | G6: Marcus Hale | H6: Prepare fee proposal
A7: ACT-4028 | B7: 2026-05-05 | C7: Lakemont College Endowment Fund | D7: Mary Brooks | E7: Email | F7: Sent Q1 attribution report | G7: Priya Venkatesan | H7: Coordinate funding paperwork
A8: ACT-4050 | B8: 2026-05-05 | C8: Maple Provincial Pension Board | D8: Aisha Fernandez | E8: Email | F8: ESG policy documentation | G8: Sofia Marchetti | H8: Send follow-up deck
A9: ACT-4054 | B9: 2026-05-03 | C9: Nordmark National Pension Fund | D9: Emma Delgado | E9: Webinar | F9: Invited to fixed income webinar | G9: Sofia Marchetti | H9: Prepare fee proposal
A10: ACT-4001 | B10: 2026-04-25 | C10: Northgate County Employees' Retirement System | D10: John Sato | E10: Call | F10: Mandate funding logistics | G10: Marcus Hale | H10: Await consultant feedback
A11: ACT-4057 | B11: 2026-04-25 | C11: Nordmark National Pension Fund | D11: Lucas Reyes | E11: Conference | F11: Hosted at Capital Group symposium | G11: Sofia Marchetti | H11: No action - relationship healthy
A12: ACT-4034 | B12: 2026-04-24 | C12: Sentinel Mutual Life General Account | D12: Anneke Hoffman | E12: Email | F12: Followed up on RFP questions | G12: Daniel Cho | H12: Await consultant feedback
... A70: ACT-4046 | B70: 2026-01-05 | C70: Beacon Wealth Model Portfolios | D70: Aisha Mitchell | E70: Email | F70: ESG policy documentation | G70: Renee Lambert | H70: Share peer benchmarking data

Sheet AUM Summary
A1: AUM by Client Type ($mm)
A3: Client Type | B3: # Accounts | C3: AUM ($mm) | D3: % of Total
A4: Public Pension (DB) | B4: =COUNTIF(Accounts!C:C,A4) -> 6 | C4: =SUMIF(Accounts!C:C,A4,Accounts!F:F) -> 3646.6 | D4: =IF($C$13=0,0,C4/$C$13) -> 0.12227475
A5: Corporate Pension (DB) | B5: =COUNTIF(Accounts!C:C,A5) -> 3 | C5: =SUMIF(Accounts!C:C,A5,Accounts!F:F) -> 2029.6 | D5: =IF($C$13=0,0,C5/$C$13) -> 0.068054857
A6: Corporate DC / 401(k) | B6: =COUNTIF(Accounts!C:C,A6) -> 3 | C6: =SUMIF(Accounts!C:C,A6,Accounts!F:F) -> 4199.7 | D6: =IF($C$13=0,0,C6/$C$13) -> 0.14082084
A7: Endowment & Foundation | B7: =COUNTIF(Accounts!C:C,A7) -> 3 | C7: =SUMIF(Accounts!C:C,A7,Accounts!F:F) -> 4591.7 | D7: =IF($C$13=0,0,C7/$C$13) -> 0.15396506
A8: Insurance General Account | B8: =COUNTIF(Accounts!C:C,A8) -> 2 | C8: =SUMIF(Accounts!C:C,A8,Accounts!F:F) -> 4064.8 | D8: =IF($C$13=0,0,C8/$C$13) -> 0.13629749
A9: Sub-Advisory | B9: =COUNTIF(Accounts!C:C,A9) -> 2 | C9: =SUMIF(Accounts!C:C,A9,Accounts!F:F) -> 3507.6 | D9: =IF($C$13=0,0,C9/$C$13) -> 0.11761392
A10: Healthcare System | B10: =COUNTIF(Accounts!C:C,A10) -> 2 | C10: =SUMIF(Accounts!C:C,A10,Accounts!F:F) -> 2790.2 | D10: =IF($C$13=0,0,C10/$C$13) -> 0.093558663
A11: Sovereign / Government | B11: =COUNTIF(Accounts!C:C,A11) -> 2 | C11: =SUMIF(Accounts!C:C,A11,Accounts!F:F) -> 2418.7 | D11: =IF($C$13=0,0,C11/$C$13) -> 0.081101834
A12: Taft-Hartley / Union | B12: =COUNTIF(Accounts!C:C,A12) -> 2 | C12: =SUMIF(Accounts!C:C,A12,Accounts!F:F) -> 2574.1 | D12: =IF($C$13=0,0,C12/$C$13) -> 0.086312578
A13: TOTAL | B13: =SUM(B4:B12) -> 25 | C13: =SUM(C4:C12) -> 29823 | D13: =SUM(D4:D12) -> 1
A16: Pipeline by Stage
A18: Stage | B18: # Opps | C18: Mandate $mm
A19: Prospecting | B19: =COUNTIF(Pipeline!F:F,A19) -> 2 | C19: =SUMIF(Pipeline!F:F,A19,Pipeline!E:E) -> 718.5
A20: Qualification | B20: =COUNTIF(Pipeline!F:F,A20) -> 3 | C20: =SUMIF(Pipeline!F:F,A20,Pipeline!E:E) -> 1023.6
A21: RFP Submitted | B21: =COUNTIF(Pipeline!F:F,A21) -> 3 | C21: =SUMIF(Pipeline!F:F,A21,Pipeline!E:E) -> 766.9
A22: Finals Presentation | B22: =COUNTIF(Pipeline!F:F,A22) -> 6 | C22: =SUMIF(Pipeline!F:F,A22,Pipeline!E:E) -> 2629.5
A23: Due Diligence | B23: =COUNTIF(Pipeline!F:F,A23) -> 5 | C23: =SUMIF(Pipeline!F:F,A23,Pipeline!E:E) -> 2678.9
A24: Won | B24: =COUNTIF(Pipeline!F:F,A24) -> 3 | C24: =SUMIF(Pipeline!F:F,A24,Pipeline!E:E) -> 922.1
A25: Lost | B25: =COUNTIF(Pipeline!F:F,A25) -> 7 | C25: =SUMIF(Pipeline!F:F,A25,Pipeline!E:E) -> 2879.9

Sheet Team & Org Chart
A1: Institutional Client Group — Team & Reporting Structure (MOCK)
A2: Fictional team. 'Direct Accounts' and 'Direct AUM' are live formulas counting accounts where the person is named Relationship Mgr on the Accounts sheet (managers oversee via reports, so they show 0 direct).
A4: Employee ID | B4: Name | C4: Title | D4: Level | E4: Reports To | F4: Manager ID | G4: Function / Segment | H4: Location | I4: Email | J4: Direct Accounts | K4: Direct AUM ($mm)
A5: E-100 | B5: Katherine Reynolds | C5: Head of Institutional Client Group | D5: 1 | E5: — (President, Capital Client Group) | F5: — | G5: Institutional Client Group (all) | H5: Los Angeles, CA | I5: k.reynolds@capitalgroup-mock.example.com | J5: =COUNTIF(Accounts!J:J,B5) -> 0 | K5: =SUMIF(Accounts!J:J,B5,Accounts!F:F) -> 0
A6: E-110 | B6: Gregory Tanaka | C6: Managing Director — Public Funds & Pensions (Americas) | D6: 2 | E6: Katherine Reynolds | F6: E-100 | G6: Public Funds & Pensions — Americas | H6: New York, NY | I6: g.tanaka@capitalgroup-mock.example.com | J6: =COUNTIF(Accounts!J:J,B6) -> 0 | K6: =SUMIF(Accounts!J:J,B6,Accounts!F:F) -> 0
A7: E-120 | B7: Helena Brandt | C7: Managing Director — Corporate DB/DC & Sub-Advisory | D7: 2 | E7: Katherine Reynolds | F7: E-100 | G7: Corporate DB/DC & Sub-Advisory | H7: Los Angeles, CA | I7: h.brandt@capitalgroup-mock.example.com | J7: =COUNTIF(Accounts!J:J,B7) -> 0 | K7: =SUMIF(Accounts!J:J,B7,Accounts!F:F) -> 0
A8: E-130 | B8: Victor Almeida | C8: Managing Director — EMEA / APAC / Sovereign | D8: 2 | E8: Katherine Reynolds | F8: E-100 | G8: EMEA / APAC / Sovereign | H8: London, UK | I8: v.almeida@capitalgroup-mock.example.com | J8: =COUNTIF(Accounts!J:J,B8) -> 0 | K8: =SUMIF(Accounts!J:J,B8,Accounts!F:F) -> 0
A9: E-140 | B9: Janet Osei | C9: Director — Client Service & Operations | D9: 2 | E9: Katherine Reynolds | F9: E-100 | G9: Client Service & Operations | H9: Irvine, CA | I9: j.osei@capitalgroup-mock.example.com | J9: =COUNTIF(Accounts!J:J,B9) -> 0 | K9: =SUMIF(Accounts!J:J,B9,Accounts!F:F) -> 0
A10: E-111 | B10: Diane Okafor | C10: Senior Relationship Director | D10: 3 | E10: Gregory Tanaka | F10: E-110 | G10: Public Funds & Pensions — Americas | H10: Chicago, IL | I10: d.okafor@capitalgroup-mock.example.com | J10: =COUNTIF(Accounts!J:J,B10) -> 2 | K10: =SUMIF(Accounts!J:J,B10,Accounts!F:F) -> 1310.6
A11: E-112 | B11: Marcus Hale | C11: Relationship Manager | D11: 3 | E11: Gregory Tanaka | F11: E-110 | G11: Public Funds & Pensions — Americas | H11: New York, NY | I11: m.hale@capitalgroup-mock.example.com | J11: =COUNTIF(Accounts!J:J,B11) -> 2 | K11: =SUMIF(Accounts!J:J,B11,Accounts!F:F) -> 2548.7
A12: E-113 | B12: Tom Brennan | C12: Relationship Manager | D12: 3 | E12: Gregory Tanaka | F12: E-110 | G12: Public Funds & Pensions — Americas | H12: San Francisco, CA | I12: t.brennan@capitalgroup-mock.example.com | J12: =COUNTIF(Accounts!J:J,B12) -> 5 | K12: =SUMIF(Accounts!J:J,B12,Accounts!F:F) -> 2748.9
A13: E-121 | B13: Sofia Marchetti | C13: Relationship Manager | D13: 3 | E13: Helena Brandt | F13: E-120 | G13: Corporate DB/DC & Sub-Advisory | H13: Los Angeles, CA | I13: s.marchetti@capitalgroup-mock.example.com | J13: =COUNTIF(Accounts!J:J,B13) -> 6 | K13: =SUMIF(Accounts!J:J,B13,Accounts!F:F) -> 7970.7
A14: E-122 | B14: Renee Lambert | C14: Relationship Manager | D14: 3 | E14: Helena Brandt | F14: E-120 | G14: Corporate DB/DC & Sub-Advisory | H14: Charlotte, NC | I14: r.lambert@capitalgroup-mock.example.com | J14: =COUNTIF(Accounts!J:J,B14) -> 2 | K14: =SUMIF(Accounts!J:J,B14,Accounts!F:F) -> 1706.2
A15: E-123 | B15: Daniel Cho | C15: Relationship Manager | D15: 3 | E15: Helena Brandt | F15: E-120 | G15: Corporate DB/DC & Sub-Advisory | H15: New York, NY | I15: d.cho@capitalgroup-mock.example.com | J15: =COUNTIF(Accounts!J:J,B15) -> 5 | K15: =SUMIF(Accounts!J:J,B15,Accounts!F:F) -> 7218.1
A16: E-131 | B16: Priya Venkatesan | C16: Relationship Manager | D16: 3 | E16: Victor Almeida | F16: E-130 | G16: EMEA / APAC / Sovereign | H16: London, UK | I16: p.venkatesan@capitalgroup-mock.example.com | J16: =COUNTIF(Accounts!J:J,B16) -> 1 | K16: =SUMIF(Accounts!J:J,B16,Accounts!F:F) -> 1651.6
... A22: E-143 | B22: Ravi Patel | C22: Onboarding & Reporting Analyst | D22: 4 | E22: Janet Osei | F22: E-140 | G22: Client Service & Operations | H22: Irvine, CA | I22: r.patel@capitalgroup-mock.example.com | J22: =COUNTIF(Accounts!J:J,B22) -> 0 | K22: =SUMIF(Accounts!J:J,B22,Accounts!F:F) -> 0
A25: Org Tree (who reports to whom)
A26: Katherine Reynolds — Head of Institutional Client Group
A27: └─ Gregory Tanaka — Managing Director — Public Funds & Pensions (Americas)
A28: └─ Diane Okafor — Senior Relationship Director
A29: └─ Marcus Hale — Relationship Manager
A30: └─ Lucas Bauer — Investment Specialist
A31: └─ Tom Brennan — Relationship Manager
A32: └─ Helena Brandt — Managing Director — Corporate DB/DC & Sub-Advisory
A33: └─ Sofia Marchetti — Relationship Manager
A34: └─ Emma Lindqvist — Client Analyst
A35: └─ Renee Lambert — Relationship Manager
A36: └─ Daniel Cho — Relationship Manager
... A49: L4 Specialist / Analyst / CSA
